{
  "Name" : "ichi",
  "Spritesheet" : "Ichi128x196",
  "Level" : "Level1",
  "Path" : "assets/spritesheets/ichi/ichi_climb_up_ledge_128x196.png",
  "Animations" : [
    {"AnimationDirection":"forward","PivotNorm":{"x":4,"y":3},"AnimationId":"None","AnimationType":"Character","FrameSize":{"height":128,"width":192},"Frames":[{"duration":100,"event":"None","height":192,"width":128,"x_sheet":0,"y_sheet":0}],"Name":"stand","Sheet_begin":0,"Sheet_end":0,"animationDuration":"100 ms","numFrames":1,"repeat":true},
    {"AnimationDirection":"forward","PivotNorm":{"x":4,"y":3},"AnimationId":"IchiLedgeHangIdle","AnimationType":"Character","FrameSize":{"height":192,"width":128},"Frames":[{"duration":100,"event":"None","height":192,"width":128,"x_sheet":256,"y_sheet":0}],"Name":"hang","Sheet_begin":2,"Sheet_end":2,"animationDuration":"100 ms","numFrames":1,"repeat":true},
    {"AnimationDirection":"forward","PivotNorm":{"x":4,"y":3},"AnimationId":"IchiLedgeClimbUp","AnimationType":"Character","FrameSize":{"height":192,"width":128},"Frames":[{"duration":100,"event":"None","height":192,"width":128,"x_sheet":384,"y_sheet":0},{"duration":100,"event":"None","height":192,"width":128,"x_sheet":512,"y_sheet":0},{"duration":100,"event":"None","height":192,"width":128,"x_sheet":640,"y_sheet":0},{"duration":100,"event":"None","height":192,"width":128,"x_sheet":0,"y_sheet":192},{"duration":100,"event":"None","height":192,"width":128,"x_sheet":128,"y_sheet":192},{"duration":100,"event":"None","height":192,"width":128,"x_sheet":256,"y_sheet":192},{"duration":100,"event":"None","height":192,"width":128,"x_sheet":384,"y_sheet":192},{"duration":100,"event":"None","height":192,"width":128,"x_sheet":512,"y_sheet":192},{"duration":100,"event":"None","height":192,"width":128,"x_sheet":640,"y_sheet":192},{"duration":100,"event":"None","height":192,"width":128,"x_sheet":0,"y_sheet":384},{"duration":100,"event":"None","height":192,"width":128,"x_sheet":128,"y_sheet":384},{"duration":100,"event":"None","height":192,"width":128,"x_sheet":256,"y_sheet":384},{"duration":100,"event":"None","height":192,"width":128,"x_sheet":384,"y_sheet":384},{"duration":100,"event":"None","height":192,"width":128,"x_sheet":512,"y_sheet":384},{"duration":100,"event":"None","height":192,"width":128,"x_sheet":640,"y_sheet":384}],"Name":"climbup","Sheet_begin":3,"Sheet_end":17,"animationDuration":"1500 ms","numFrames":15,"repeat":false}
    ]
}
